panoptes_cli/__init__.py
panoptes_cli/commands/__init__.py
panoptes_cli/commands/configure.py
panoptes_cli/commands/inaturalist.py
panoptes_cli/commands/info.py
panoptes_cli/commands/project.py
panoptes_cli/commands/subject.py
panoptes_cli/commands/subject_set.py
panoptes_cli/commands/user.py
panoptes_cli/commands/workflow.py
panoptes_cli/commands/tests/__init__.py
panoptes_cli/commands/tests/test_project.py
panoptes_cli/scripts/__init__.py
panoptes_cli/scripts/panoptes.py
panoptescli-1.2.1.dist-info/LICENSE
panoptescli-1.2.1.dist-info/METADATA
panoptescli-1.2.1.dist-info/WHEEL
panoptescli-1.2.1.dist-info/entry_points.txt
panoptescli-1.2.1.dist-info/top_level.txt
panoptescli-1.2.1.dist-info/RECORD
