Metadata-Version: 2.1
Name: panoptescli
Version: 1.2.1
Summary: A command-line client for Panoptes, the API behind the Zooniverse
Home-page: https://github.com/zooniverse/panoptes-cli
Author: Adam McMaster / Zooniverse
Author-email: contact@zooniverse.org
License: UNKNOWN
Platform: UNKNOWN
License-File: LICENSE
Requires-Dist: Click<8.2,>=6.7
Requires-Dist: PyYAML<6.1,>=5.1
Requires-Dist: panoptes-client<2.0,>=1.7
Requires-Dist: humanize<4.8,>=0.5.1
Requires-Dist: pathvalidate<2.6,>=0.29.0
